porscheTool-0.1.data/purelib/datasets/__init__.py
porscheTool-0.1.data/purelib/datasets/odps.py
porscheTool-0.1.data/purelib/examples/__init__.py
porscheTool-0.1.data/purelib/examples/mnist.py
porscheTool-0.1.data/purelib/util/__init__.py
porscheTool-0.1.data/purelib/util/checkpoint.py
porscheTool-0.1.dist-info/METADATA
porscheTool-0.1.dist-info/WHEEL
porscheTool-0.1.dist-info/top_level.txt
porscheTool-0.1.dist-info/RECORD
