Metadata-Version: 2.1
Name: porscheTool
Version: 0.1
Summary: porscheTool
Home-page: UNKNOWN
Author: xingbi
Author-email: UNKNOWN
License: UNKNOWN
Platform: UNKNOWN
